Metadata-Version: 2.1
Name: pladif
Version: 1.3
Summary: PLADIF is a simple tool that plot attrakdiff graphs from CSV files (like those from Usabilla)
Home-page: https://github.com/thilaire/PLADIF
Author: Thibault Hilaire
Author-email: thibault@docmatic.fr
License: MIT
Keywords: CSV,attrakdiff,Usabilla
Platform: UNKNOWN
Classifier: Development Status :: 5 - Production/Stable
Classifier: License :: OSI Approved :: MIT License
Classifier: Programming Language :: Python :: 3.9
Classifier: Topic :: Scientific/Engineering :: Human Machine Interfaces
Classifier: Intended Audience :: Other Audience
License-File: LICENSE
